autopost/__init__.py
autopost/admin.py
autopost/apps.py
autopost/forms.py
autopost/models.py
autopost/tests.py
autopost/urls.py
autopost/views.py
autopost/management/__init__.py
autopost/management/commands/__init__.py
autopost/management/commands/autopost.py
autopost/migrations/0001_initial.py
autopost/migrations/0002_auto_20181023_1435.py
autopost/migrations/0003_auto_20181104_2045.py
autopost/migrations/0004_auto_20181104_2104.py
autopost/migrations/0005_auto_20190104_1005.py
autopost/migrations/0006_auto_20190201_2356.py
autopost/migrations/0007_auto_20190507_2329.py
autopost/migrations/0008_auto_20190829_0935.py
autopost/migrations/0009_auto_20190903_0948.py
autopost/migrations/0010_auto_20190906_2318.py
autopost/migrations/__init__.py
autopost/static/qt_admin/css/article.css
autopost/static/qt_admin/css/bootstrap.css
autopost/static/qt_admin/css/bootstrap.min.css
autopost/static/qt_admin/js/article.js
autopost/static/qt_admin/js/autopost.js
autopost/static/qt_admin/js/bootstrap.min.js
autopost/static/qt_admin/js/category.js
autopost/static/qt_admin/js/jquery-1.12.4.min.js
autopost/static/qt_admin/layui/layui.all.js
autopost/static/qt_admin/layui/layui.js
autopost/static/qt_admin/layui/css/layui.css
autopost/static/qt_admin/layui/css/layui.mobile.css
autopost/static/qt_admin/layui/css/modules/code.css
autopost/static/qt_admin/layui/css/modules/laydate/default/laydate.css
autopost/static/qt_admin/layui/css/modules/layer/default/icon-ext.png
autopost/static/qt_admin/layui/css/modules/layer/default/icon.png
autopost/static/qt_admin/layui/css/modules/layer/default/layer.css
autopost/static/qt_admin/layui/css/modules/layer/default/loading-0.gif
autopost/static/qt_admin/layui/css/modules/layer/default/loading-1.gif
autopost/static/qt_admin/layui/css/modules/layer/default/loading-2.gif
autopost/static/qt_admin/layui/font/iconfont.eot
autopost/static/qt_admin/layui/font/iconfont.svg
autopost/static/qt_admin/layui/font/iconfont.ttf
qitian_module-2.0.5.dist-info/LICENSE
qitian_module-2.0.5.dist-info/METADATA
qitian_module-2.0.5.dist-info/WHEEL
qitian_module-2.0.5.dist-info/top_level.txt
qitian_module-2.0.5.dist-info/RECORD
