Metadata-Version: 2.1
Name: qitian-module
Version: 2.0.5
Summary: 起田(苏州)营销策划有限公司Django项目公用底层框架.
Home-page: https://gitee.com/qtch/django_module
Author: Peter Han
Author-email: peter@qitian.com
License: MIT License
Keywords: framework qitian common module
Platform: UNKNOWN
Classifier: Development Status :: 5 - Production/Stable
Classifier: Environment :: Web Environment
Classifier: Framework :: Django
Classifier: Framework :: Django :: 1.11
Classifier: Framework :: Django :: 2.0
Classifier: Intended Audience :: Developers
Classifier: License :: OSI Approved :: MIT License
Classifier: Operating System :: OS Independent
Classifier: Programming Language :: Python
Classifier: Programming Language :: Python :: 3.5
Classifier: Programming Language :: Python :: 3.6
Classifier: Programming Language :: Python :: Implementation :: CPython
Classifier: Programming Language :: Python :: Implementation :: PyPy
Classifier: Topic :: Utilities
Requires-Python: >=3.6, !=3.0.*
Requires-Dist: django
Requires-Dist: beautifulsoup4
Requires-Dist: django-environ
Requires-Dist: django-redis
Requires-Dist: django-smart-selects (==1.5.3)
Requires-Dist: django-uuslug
Requires-Dist: shortuuid
Requires-Dist: qiniu (==7.2.2)
Requires-Dist: textrank4zh (==0.3)
Requires-Dist: yunpian-python-sdk
Requires-Dist: pycryptodomex (==3.6.6)
Requires-Dist: python-crontab (==2.3.5)
Requires-Dist: mammoth (==1.4.8)
Requires-Dist: django-notifications-hq
Requires-Dist: django-taggit (==0.23.0)
Requires-Dist: qitian-simditor
Requires-Dist: djangorestframework
Requires-Dist: django-taggit-labels
Requires-Dist: django-taggit-helpers
Requires-Dist: pillow
Requires-Dist: mysqlclient
Requires-Dist: django-mptt
Requires-Dist: lxml
Requires-Dist: gunicorn
